findimport/__init__.py
findimport/__main__.py
findimport-0.1.dist-info/METADATA
findimport-0.1.dist-info/WHEEL
findimport-0.1.dist-info/top_level.txt
findimport-0.1.dist-info/RECORD
