Metadata-Version: 2.1
Name: findimport
Version: 0.1
Summary: This is a simple library to find the recursive import link of source code
Home-page: https://github.com/vigneshgig/Python-Find-imported-Module
Author: VigneshAmudha
Author-email: vigneshgig@gmail.com
License: MIT
Download-URL: https://github.com/vigneshgig/Python-Find-imported-Module/archive/v_01.tar.gz
Keywords: Module Finder,Import Finder,Module Tracker,Import Tracker
Platform: UNKNOWN
Classifier: Development Status :: 3 - Alpha
Classifier: Topic :: Software Development :: Build Tools
Classifier: License :: OSI Approved :: MIT License
Classifier: Programming Language :: Python :: 3.7
